CHANGES.txt
MANIFEST.in
README.txt
setup.py
collective/__init__.py
collective.portlet.customizablerecent.egg-info/PKG-INFO
collective.portlet.customizablerecent.egg-info/SOURCES.txt
collective.portlet.customizablerecent.egg-info/dependency_links.txt
collective.portlet.customizablerecent.egg-info/entry_points.txt
collective.portlet.customizablerecent.egg-info/namespace_packages.txt
collective.portlet.customizablerecent.egg-info/not-zip-safe
collective.portlet.customizablerecent.egg-info/requires.txt
collective.portlet.customizablerecent.egg-info/top_level.txt
collective/portlet/__init__.py
collective/portlet/customizablerecent/__init__.py
collective/portlet/customizablerecent/all_recent.pt
collective/portlet/customizablerecent/configure.zcml
collective/portlet/customizablerecent/customizablerecent.py
collective/portlet/customizablerecent/recent.pt
collective/portlet/customizablerecent/version.txt
collective/portlet/customizablerecent/locales/collective.portlet.customizablerecent.pot
collective/portlet/customizablerecent/locales/plone.pot
collective/portlet/customizablerecent/locales/update.sh
collective/portlet/customizablerecent/locales/fr/LC_MESSAGES/collective.portlet.customizablerecent.po
collective/portlet/customizablerecent/locales/fr/LC_MESSAGES/plone.po
collective/portlet/customizablerecent/profiles/default/metadata.xml
collective/portlet/customizablerecent/profiles/default/portlets.xml
collective/portlet/customizablerecent/tests/__init__.py
collective/portlet/customizablerecent/tests/base.py
collective/portlet/customizablerecent/tests/test_portlet.py
docs/INSTALL.txt
docs/LICENSE.GPL
docs/LICENSE.txt