Metadata-Version: 1.1
Name: collective.portlet.customizablerecent
Version: 1.1.4
Summary: A recent items portlet with parameters
Home-page: http://pypi.python.org/pypi/collective.portlet.customizablerecent
Author: Thomas Desvenain
Author-email: thomasdesvenain@ecreall.com
License: GPL
Keywords: portlets
Platform: UNKNOWN
Classifier: Framework :: Plone
Classifier: Programming Language :: Python
